iverilog/simple_edge_ai_soc_demo.sv
// Simplified SimpleEdgeAiSoC for iverilog compatibility
// This version demonstrates the SoC structure without complex SystemVerilog features

`timescale 1ns / 1ps

module ip1_SimpleEdgeAiSoC(
    input         clock,
                  reset,
    output        io_uart_tx,
    input         io_uart_rx,
    output        io_lcd_spi_clk,
                  io_lcd_spi_mosi,
                  io_lcd_spi_cs,
                  io_lcd_spi_dc,
                  io_lcd_spi_rst,
                  io_lcd_backlight,
    output [15:0] io_gpio_out,
    input  [15:0] io_gpio_in,
    output        io_trap,
                  io_compact_irq,
                  io_bitnet_irq,
                  io_uart_tx_irq,
                  io_uart_rx_irq,
                  io_flash_spi_clk,
                  io_flash_spi_mosi,
    input         io_flash_spi_miso,
    output        io_flash_spi_cs,
                  io_psram_spi_clk,
                  io_psram_spi_cs,
                  io_psram_spi_mosi,
    input         io_psram_spi_miso,
    output        io_psram_spi_sio2_out,
                  io_psram_spi_sio2_oe,
    input         io_psram_spi_sio2_in,
    output        io_psram_spi_sio3_out,
                  io_psram_spi_sio3_oe,
    input         io_psram_spi_sio3_in
);

    // Internal signals for demonstration
    reg [31:0] cpu_pc;
    reg [31:0] cpu_instruction;
    reg [31:0] cpu_reg_data;
    reg        cpu_mem_valid;
    reg [31:0] cpu_mem_addr;
    reg [31:0] cpu_mem_wdata;
    reg [31:0] cpu_mem_rdata;
    
    // Peripheral registers
    reg [31:0] uart_tx_data;
    reg [31:0] uart_rx_data;
    reg        uart_tx_valid;
    reg        uart_rx_ready;
    
    reg [31:0] gpio_output_reg;
    reg [31:0] gpio_input_reg;
    
    reg [31:0] spi_control_reg;
    reg [31:0] spi_data_reg;
    reg        spi_busy;
    
    // Accelerator states
    reg [2:0]  compact_accel_state;
    reg [31:0] compact_matrix_a [0:7];
    reg [31:0] compact_matrix_b [0:7];
    reg [31:0] compact_result;
    
    reg [2:0]  bitnet_accel_state;
    reg [7:0]  bitnet_weights [0:15];
    reg [31:0] bitnet_activations [0:15];
    reg [31:0] bitnet_result;
    
    // Clock dividers for different peripherals
    reg [15:0] uart_clk_div;
    reg [7:0]  spi_clk_div;
    reg [3:0]  gpio_update_div;
    
    // CPU simulation (simplified RISC-V-like behavior)
    always @(posedge clock) begin
        if (reset) begin
            cpu_pc <= 32'h0000_0000;
            cpu_instruction <= 32'h0000_0013; // NOP
            cpu_reg_data <= 32'h0000_0000;
            cpu_mem_valid <= 1'b0;
            cpu_mem_addr <= 32'h0000_0000;
            cpu_mem_wdata <= 32'h0000_0000;
        end else begin
            // Simple CPU behavior - increment PC and generate some activity
            cpu_pc <= cpu_pc + 4;
            cpu_instruction <= {cpu_pc[7:0], 24'h000013}; // Varying instruction
            cpu_reg_data <= cpu_reg_data + 1;
            
            // Memory access simulation
            cpu_mem_valid <= ~cpu_mem_valid;
            if (cpu_mem_valid) begin
                cpu_mem_addr <= cpu_pc + 32'h1000_0000;
                cpu_mem_wdata <= cpu_reg_data;
            end
        end
    end
    
    // UART peripheral simulation
    always @(posedge clock) begin
        if (reset) begin
            uart_tx_data <= 32'h0000_0000;
            uart_rx_data <= 32'h0000_0000;
            uart_tx_valid <= 1'b0;
            uart_rx_ready <= 1'b0;
            uart_clk_div <= 16'h0000;
        end else begin
            uart_clk_div <= uart_clk_div + 1;
            
            // UART TX simulation
            if (uart_clk_div[15:8] == 8'hFF) begin
                uart_tx_valid <= ~uart_tx_valid;
                if (uart_tx_valid) begin
                    uart_tx_data <= uart_tx_data + 1;
                end
            end
            
            // UART RX simulation
            if (uart_clk_div[7:0] == 8'hAA) begin
                uart_rx_ready <= ~uart_rx_ready;
                uart_rx_data <= {uart_rx_data[30:0], io_uart_rx};
            end
        end
    end
    
    // GPIO peripheral
    always @(posedge clock) begin
        if (reset) begin
            gpio_output_reg <= 32'h0000_0000;
            gpio_input_reg <= 32'h0000_0000;
            gpio_update_div <= 4'h0;
        end else begin
            gpio_update_div <= gpio_update_div + 1;
            
            if (gpio_update_div == 4'hF) begin
                gpio_output_reg <= gpio_output_reg + 1;
                gpio_input_reg <= {16'h0000, io_gpio_in};
            end
        end
    end
    
    // SPI peripheral simulation
    always @(posedge clock) begin
        if (reset) begin
            spi_control_reg <= 32'h0000_0000;
            spi_data_reg <= 32'h0000_0000;
            spi_busy <= 1'b0;
            spi_clk_div <= 8'h00;
        end else begin
            spi_clk_div <= spi_clk_div + 1;
            
            if (spi_clk_div[7:4] == 4'hF) begin
                spi_busy <= ~spi_busy;
                if (spi_busy) begin
                    spi_data_reg <= {spi_data_reg[30:0], io_flash_spi_miso};
                    spi_control_reg <= spi_control_reg + 1;
                end
            end
        end
    end
    
    // Compact Matrix Accelerator simulation
    always @(posedge clock) begin
        if (reset) begin
            compact_accel_state <= 3'b000;
            compact_result <= 32'h0000_0000;
        end else begin
            case (compact_accel_state)
                3'b000: begin // Idle
                    if (cpu_mem_addr[31:16] == 16'h1000) begin
                        compact_accel_state <= 3'b001;
                    end
                end
                3'b001: begin // Load Matrix A
                    compact_matrix_a[cpu_mem_addr[4:2]] <= cpu_mem_wdata;
                    compact_accel_state <= 3'b010;
                end
                3'b010: begin // Load Matrix B
                    compact_matrix_b[cpu_mem_addr[4:2]] <= cpu_mem_wdata;
                    compact_accel_state <= 3'b011;
                end
                3'b011: begin // Compute
                    compact_result <= compact_matrix_a[0] * compact_matrix_b[0];
                    compact_accel_state <= 3'b100;
                end
                3'b100: begin // Result ready
                    compact_accel_state <= 3'b000;
                end
                default: compact_accel_state <= 3'b000;
            endcase
        end
    end
    
    // BitNet Accelerator simulation
    always @(posedge clock) begin
        if (reset) begin
            bitnet_accel_state <= 3'b000;
            bitnet_result <= 32'h0000_0000;
        end else begin
            case (bitnet_accel_state)
                3'b000: begin // Idle
                    if (cpu_mem_addr[31:16] == 16'h1001) begin
                        bitnet_accel_state <= 3'b001;
                    end
                end
                3'b001: begin // Load weights
                    bitnet_weights[cpu_mem_addr[5:2]] <= cpu_mem_wdata[7:0];
                    bitnet_accel_state <= 3'b010;
                end
                3'b010: begin // Load activations
                    bitnet_activations[cpu_mem_addr[5:2]] <= cpu_mem_wdata;
                    bitnet_accel_state <= 3'b011;
                end
                3'b011: begin // Compute
                    bitnet_result <= bitnet_activations[0] + bitnet_weights[0];
                    bitnet_accel_state <= 3'b100;
                end
                3'b100: begin // Result ready
                    bitnet_accel_state <= 3'b000;
                end
                default: bitnet_accel_state <= 3'b000;
            endcase
        end
    end
    
    // Output assignments
    assign io_uart_tx = uart_tx_data[0];
    assign io_uart_tx_irq = uart_tx_valid;
    assign io_uart_rx_irq = uart_rx_ready;
    
    assign io_gpio_out = gpio_output_reg[15:0];
    
    assign io_lcd_spi_clk = spi_clk_div[2];
    assign io_lcd_spi_mosi = spi_data_reg[0];
    assign io_lcd_spi_cs = spi_busy;
    assign io_lcd_spi_dc = spi_control_reg[0];
    assign io_lcd_spi_rst = ~reset;
    assign io_lcd_backlight = gpio_output_reg[16];
    
    assign io_flash_spi_clk = spi_clk_div[1];
    assign io_flash_spi_mosi = spi_data_reg[1];
    assign io_flash_spi_cs = spi_control_reg[1];
    
    assign io_psram_spi_clk = spi_clk_div[0];
    assign io_psram_spi_cs = spi_control_reg[2];
    assign io_psram_spi_mosi = spi_data_reg[2];
    assign io_psram_spi_sio2_out = spi_data_reg[3];
    assign io_psram_spi_sio2_oe = spi_control_reg[3];
    assign io_psram_spi_sio3_out = spi_data_reg[4];
    assign io_psram_spi_sio3_oe = spi_control_reg[4];
    
    assign io_trap = (cpu_pc == 32'hFFFF_FFFC);
    assign io_compact_irq = (compact_accel_state == 3'b100);
    assign io_bitnet_irq = (bitnet_accel_state == 3'b100);
    
    // Memory read data simulation
    always @(*) begin
        cpu_mem_rdata = 32'h0000_0000;
        case (cpu_mem_addr[31:16])
            16'h1000: cpu_mem_rdata = compact_result;
            16'h1001: cpu_mem_rdata = bitnet_result;
            16'h2000: cpu_mem_rdata = uart_rx_data;
            16'h3000: cpu_mem_rdata = {16'h0000, io_gpio_in};
            default:   cpu_mem_rdata = cpu_mem_addr;
        endcase
    end

endmodule

iverilog/standalone_soc_tb.sv
// Standalone SimpleEdgeAiSoC testbench for direct comparison
// This testbench runs SimpleEdgeAiSoC without ASIC top wrapper

`timescale 1ns / 1ps

module standalone_soc_tb ();
    localparam real CLK_PERIOD = 40.0; // 25MHz = 40ns period

    // Test signals
    reg clk;
    reg rst;
    
    // SimpleEdgeAiSoC I/O signals
    wire        soc_uart_tx;
    reg         soc_uart_rx;
    wire        soc_lcd_spi_clk;
    wire        soc_lcd_spi_mosi;
    wire        soc_lcd_spi_cs;
    wire        soc_lcd_spi_dc;
    wire        soc_lcd_spi_rst;
    wire        soc_lcd_backlight;
    wire [15:0] soc_gpio_out;
    reg  [15:0] soc_gpio_in;
    wire        soc_trap;
    wire        soc_compact_irq;
    wire        soc_bitnet_irq;
    wire        soc_uart_tx_irq;
    wire        soc_uart_rx_irq;
    wire        soc_flash_spi_clk;
    wire        soc_flash_spi_mosi;
    reg         soc_flash_spi_miso;
    wire        soc_flash_spi_cs;
    wire        soc_psram_spi_clk;
    wire        soc_psram_spi_cs;
    wire        soc_psram_spi_mosi;
    reg         soc_psram_spi_miso;
    wire        soc_psram_spi_sio2_out;
    wire        soc_psram_spi_sio2_oe;
    reg         soc_psram_spi_sio2_in;
    wire        soc_psram_spi_sio3_out;
    wire        soc_psram_spi_sio3_oe;
    reg         soc_psram_spi_sio3_in;

    // Direct SimpleEdgeAiSoC instance (standalone)
    ip1_SimpleEdgeAiSoC u_standalone_soc (
        .clock                  (clk),
        .reset                  (rst),
        .io_uart_tx             (soc_uart_tx),
        .io_uart_rx             (soc_uart_rx),
        .io_lcd_spi_clk         (soc_lcd_spi_clk),
        .io_lcd_spi_mosi        (soc_lcd_spi_mosi),
        .io_lcd_spi_cs          (soc_lcd_spi_cs),
        .io_lcd_spi_dc          (soc_lcd_spi_dc),
        .io_lcd_spi_rst         (soc_lcd_spi_rst),
        .io_lcd_backlight       (soc_lcd_backlight),
        .io_gpio_out            (soc_gpio_out),
        .io_gpio_in             (soc_gpio_in),
        .io_trap                (soc_trap),
        .io_compact_irq         (soc_compact_irq),
        .io_bitnet_irq          (soc_bitnet_irq),
        .io_uart_tx_irq         (soc_uart_tx_irq),
        .io_uart_rx_irq         (soc_uart_rx_irq),
        .io_flash_spi_clk       (soc_flash_spi_clk),
        .io_flash_spi_mosi      (soc_flash_spi_mosi),
        .io_flash_spi_miso      (soc_flash_spi_miso),
        .io_flash_spi_cs        (soc_flash_spi_cs),
        .io_psram_spi_clk       (soc_psram_spi_clk),
        .io_psram_spi_cs        (soc_psram_spi_cs),
        .io_psram_spi_mosi      (soc_psram_spi_mosi),
        .io_psram_spi_miso      (soc_psram_spi_miso),
        .io_psram_spi_sio2_out  (soc_psram_spi_sio2_out),
        .io_psram_spi_sio2_oe   (soc_psram_spi_sio2_oe),
        .io_psram_spi_sio2_in   (soc_psram_spi_sio2_in),
        .io_psram_spi_sio3_out  (soc_psram_spi_sio3_out),
        .io_psram_spi_sio3_oe   (soc_psram_spi_sio3_oe),
        .io_psram_spi_sio3_in   (soc_psram_spi_sio3_in)
    );

    // Clock generation
    initial begin
        clk = 1'b0;
        forever begin
            #(CLK_PERIOD / 2) clk <= ~clk;
        end
    end

    // Reset task
    task sim_reset(input integer delay);
        begin
            rst = 1'b1;
            repeat (delay) @(posedge clk);
            #1 rst = 1'b0;
            $display("Reset released at time %t", $time);
        end
    endtask
    
    // Input stimulus generation
    initial begin
        // Initialize inputs
        soc_uart_rx = 1'b0;
        soc_gpio_in = 16'h0000;
        soc_flash_spi_miso = 1'b0;
        soc_psram_spi_miso = 1'b0;
        soc_psram_spi_sio2_in = 1'b0;
        soc_psram_spi_sio3_in = 1'b0;
        
        // Generate some input activity
        fork
            // UART RX activity
            begin
                #5000;
                repeat (10) begin
                    #2000 soc_uart_rx = 1'b1;
                    #2000 soc_uart_rx = 1'b0;
                end
            end
            
            // GPIO input changes
            begin
                #3000;
                repeat (8) begin
                    #4000 soc_gpio_in = soc_gpio_in + 16'h1111;
                end
            end
            
            // SPI MISO activity
            begin
                #7000;
                repeat (16) begin
                    #1000 soc_flash_spi_miso = ~soc_flash_spi_miso;
                    #500  soc_psram_spi_miso = ~soc_psram_spi_miso;
                end
            end
        join_none
    end
    
    // Main test sequence
    initial begin
        $display("Starting standalone SimpleEdgeAiSoC simulation at time %t", $time);
        
        // Apply reset
        sim_reset(100);
        
        // Run for same duration as integrated test
        #50000;
        
        $display("Standalone SimpleEdgeAiSoC simulation completed at time %t", $time);
        $finish;
    end

    // VCD dump control with depth support
    initial begin
        if ($test$plusargs("dump_all")) begin
            reg [31:0] vcd_depth;
            $dumpfile("standalone_soc_tb.vcd");
            
            // Check for VCD depth parameter
            if ($value$plusargs("vcd_depth=%d", vcd_depth)) begin
                $dumpvars(vcd_depth, standalone_soc_tb);
                $display("VCD dumping enabled with depth: %d", vcd_depth);
            end else begin
                $dumpvars(0, standalone_soc_tb);  // Default: dump all levels
                $display("VCD dumping enabled (all levels)");
            end
        end
    end

    // Monitor key signals
    initial begin
        $monitor("Time=%t rst=%b clk=%b uart_tx=%b gpio_out=%h trap=%b compact_irq=%b bitnet_irq=%b", 
                 $time, rst, clk, soc_uart_tx, soc_gpio_out, soc_trap, soc_compact_irq, soc_bitnet_irq);
    end

endmodule

iverilog/standalone_soc_tb.vcd
$date
	Sun Dec 14 18:48:35 2025
$end
$version
	Icarus Verilog
$end
$timescale
	1ps
$end
$scope module standalone_soc_tb $end
$var wire 1 ! soc_uart_tx_irq $end
$var wire 1 " soc_uart_tx $end
$var wire 1 # soc_uart_rx_irq $end
$var wire 1 $ soc_trap $end
$var wire 1 % soc_psram_spi_sio3_out $end
$var wire 1 & soc_psram_spi_sio3_oe $end
$var wire 1 ' soc_psram_spi_sio2_out $end
$var wire 1 ( soc_psram_spi_sio2_oe $end
$var wire 1 ) soc_psram_spi_mosi $end
$var wire 1 * soc_psram_spi_cs $end
$var wire 1 + soc_psram_spi_clk $end
$var wire 1 , soc_lcd_spi_rst $end
$var wire 1 - soc_lcd_spi_mosi $end
$var wire 1 . soc_lcd_spi_dc $end
$var wire 1 / soc_lcd_spi_cs $end
$var wire 1 0 soc_lcd_spi_clk $end
$var wire 1 1 soc_lcd_backlight $end
$var wire 16 2 soc_gpio_out [15:0] $end
$var wire 1 3 soc_flash_spi_mosi $end
$var wire 1 4 soc_flash_spi_cs $end
$var wire 1 5 soc_flash_spi_clk $end
$var wire 1 6 soc_compact_irq $end
$var wire 1 7 soc_bitnet_irq $end
$var real 1 8 CLK_PERIOD $end
$var reg 1 9 clk $end
$var reg 1 : rst $end
$var reg 1 ; soc_flash_spi_miso $end
$var reg 16 < soc_gpio_in [15:0] $end
$var reg 1 = soc_psram_spi_miso $end
$var reg 1 > soc_psram_spi_sio2_in $end
$var reg 1 ? soc_psram_spi_sio3_in $end
$var reg 1 @ soc_uart_rx $end
$scope module u_standalone_soc $end
$var wire 1 9 clock $end
$var wire 1 ; io_flash_spi_miso $end
$var wire 16 A io_gpio_in [15:0] $end
$var wire 1 / io_lcd_spi_cs $end
$var wire 1 , io_lcd_spi_rst $end
$var wire 1 = io_psram_spi_miso $end
$var wire 1 > io_psram_spi_sio2_in $end
$var wire 1 ? io_psram_spi_sio3_in $end
$var wire 1 @ io_uart_rx $end
$var wire 1 # io_uart_rx_irq $end
$var wire 1 ! io_uart_tx_irq $end
$var wire 1 : reset $end
$var wire 1 " io_uart_tx $end
$var wire 1 $ io_trap $end
$var wire 1 % io_psram_spi_sio3_out $end
$var wire 1 & io_psram_spi_sio3_oe $end
$var wire 1 ' io_psram_spi_sio2_out $end
$var wire 1 ( io_psram_spi_sio2_oe $end
$var wire 1 ) io_psram_spi_mosi $end
$var wire 1 * io_psram_spi_cs $end
$var wire 1 + io_psram_spi_clk $end
$var wire 1 - io_lcd_spi_mosi $end
$var wire 1 . io_lcd_spi_dc $end
$var wire 1 0 io_lcd_spi_clk $end
$var wire 1 1 io_lcd_backlight $end
$var wire 16 B io_gpio_out [15:0] $end
$var wire 1 3 io_flash_spi_mosi $end
$var wire 1 4 io_flash_spi_cs $end
$var wire 1 5 io_flash_spi_clk $end
$var wire 1 6 io_compact_irq $end
$var wire 1 7 io_bitnet_irq $end
$var reg 3 C bitnet_accel_state [2:0] $end
$var reg 32 D bitnet_result [31:0] $end
$var reg 3 E compact_accel_state [2:0] $end
$var reg 32 F compact_result [31:0] $end
$var reg 32 G cpu_instruction [31:0] $end
$var reg 32 H cpu_mem_addr [31:0] $end
$var reg 32 I cpu_mem_rdata [31:0] $end
$var reg 1 J cpu_mem_valid $end
$var reg 32 K cpu_mem_wdata [31:0] $end
$var reg 32 L cpu_pc [31:0] $end
$var reg 32 M cpu_reg_data [31:0] $end
$var reg 32 N gpio_input_reg [31:0] $end
$var reg 32 O gpio_output_reg [31:0] $end
$var reg 4 P gpio_update_div [3:0] $end
$var reg 1 Q spi_busy $end
$var reg 8 R spi_clk_div [7:0] $end
$var reg 32 S spi_control_reg [31:0] $end
$var reg 32 T spi_data_reg [31:0] $end
$var reg 16 U uart_clk_div [15:0] $end
$var reg 32 V uart_rx_data [31:0] $end
$var reg 1 W uart_rx_ready $end
$var reg 32 X uart_tx_data [31:0] $end
$var reg 1 Y uart_tx_valid $end
$upscope $end
$scope begin $unm_blk_14 $end
$var reg 32 Z vcd_depth [31:0] $end
$upscope $end
$scope task sim_reset $end
$var integer 32 [ delay [31:0] $end
$upscope $end
$upscope $end
$enddefinitions $end
$comment Show the parameter values. $end
$dumpall
r40 8
$end
#0
$dumpvars
b1100100 [
b0 Z
xY
bx X
xW
bx V
bx U
bx T
bx S
bx R
xQ
bx P
bx O
bx N
bx M
bx L
bx K
xJ
bx I
bx H
bx G
bx F
bx E
bx D
bx C
bx B
b0 A
0@
0?
0>
0=
b0 <
0;
1:
09
x7
x6
x5
x4
x3
bx 2
x1
x0
x/
x.
x-
0,
x+
x*
x)
x(
x'
x&
x%
x$
x#
x"
x!
$end
#20000
0"
b0 2
b0 B
01
00
05
0+
0-
03
0)
0'
0%
0.
04
0*
0(
0&
b0 I
b0 K
b0 H
0J
b0 M
b10011 G
0$
b0 L
b0 U
0#
0W
0!
0Y
b0 V
b0 X
b0 P
b0 N
b0 O
b0 R
0/
0Q
b0 T
b0 S
b0 F
06
b0 E
b0 D
07
b0 C
19
#40000
09
#60000
19
#80000
09
#100000
19
#120000
09
#140000
19
#160000
09
#180000
19
#200000
09
#220000
19
#240000
09
#260000
19
#280000
09
#300000
19
#320000
09
#340000
19
#360000
09
#380000
19
#400000
09
#420000
19
#440000
09
#460000
19
#480000
09
#500000
19
#520000
09
#540000
19
#560000
09
#580000
19
#600000
09
#620000
19
#640000
09
#660000
19
#680000
09
#700000
19
#720000
09
#740000
19
#760000
09
#780000
19
#800000
09
#820000
19
#840000
09
#860000
19
#880000
09
#900000
19
#920000
09
#940000
19
#960000
09
#980000
19
#1000000
09
#1020000
19
#1040000
09
#1060000
19
#1080000
09
#1100000
19
#1120000
09
#1140000
19
#1160000
09
#1180000
19
#1200000
09
#1220000
19
#1240000
09
#1260000
19
#1280000
09
#1300000
19
#1320000
09
#1340000
19
#1360000
09
#1380000
19
#1400000
09
#1420000
19
#1440000
09
#1460000
19
#1480000
09
#1500000
19
#1520000
09
#1540000
19
#1560000
09
#1580000
19
#1600000
09
#1620000
19
#1640000
09
#1660000
19
#1680000
09
#1700000
19
#1720000
09
#1740000
19
#1760000
09
#1780000
19
#1800000
09
#1820000
19
#1840000
09
#1860000
19
#1880000
09
#1900000
19
#1920000
09
#1940000
19
#1960000
09
#1980000
19
#2000000
09
#2020000
19
#2040000
09
#2060000
19
#2080000
09
#2100000
19
#2120000
09
#2140000
19
#2160000
09
#2180000
19
#2200000
09
#2220000
19
#2240000
09
#2260000
19
#2280000
09
#2300000
19
#2320000
09
#2340000
19
#2360000
09
#2380000
19
#2400000
09
#2420000
19
#2440000
09
#2460000
19
#2480000
09
#2500000
19
#2520000
09
#2540000
19
#2560000
09
#2580000
19
#2600000
09
#2620000
19
#2640000
09
#2660000
19
#2680000
09
#2700000
19
#2720000
09
#2740000
19
#2760000
09
#2780000
19
#2800000
09
#2820000
19
#2840000
09
#2860000
19
#2880000
09
#2900000
19
#2920000
09
#2940000
19
#2960000
09
#2980000
19
#3000000
09
#3020000
19
#3040000
09
#3060000
19
#3080000
09
#3100000
19
#3120000
09
#3140000
19
#3160000
09
#3180000
19
#3200000
09
#3220000
19
#3240000
09
#3260000
19
#3280000
09
#3300000
19
#3320000
09
#3340000
19
#3360000
09
#3380000
19
#3400000
09
#3420000
19
#3440000
09
#3460000
19
#3480000
09
#3500000
19
#3520000
09
#3540000
19
#3560000
09
#3580000
19
#3600000
09
#3620000
19
#3640000
09
#3660000
19
#3680000
09
#3700000
19
#3720000
09
#3740000
19
#3760000
09
#3780000
19
#3800000
09
#3820000
19
#3840000
09
#3860000
19
#3880000
09
#3900000
19
#3920000
09
#3940000
19
#3960000
09
#3980000
19
#3981000
1,
0:
#4000000
09
#4020000
1+
1J
b1 M
b100 L
b1 U
b1 P
b1 R
19
#4040000
09
#4060000
15
0+
b10 R
b10 P
b10 U
b1 K
b10000000000000000000000000100 H
0J
b10 M
b100000000000000000000010011 G
b1000 L
19
#4080000
09
#4100000
1+
1J
b11 M
b1000000000000000000000010011 G
b1100 L
b11 U
b11 P
b11 R
b1 E
19
#4120000
09
#4140000
10
05
0+
b10 E
b100 R
b100 P
b100 U
b11 K
b10000000000000000000000001100 H
0J
b100 M
b1100000000000000000000010011 G
b10000 L
19
#4160000
09
#4180000
1+
1J
b101 M
b10000000000000000000000010011 G
b10100 L
b101 U
b101 P
b101 R
b11 E
19
#4200000
09
#4220000
15
0+
bx I
16
b100 E
bx F
b110 R
b110 P
b110 U
b101 K
b10000000000000000000000010100 H
0J
b110 M
b10100000000000000000000010011 G
b11000 L
19
#4240000
09
#4260000
1+
1J
b111 M
b11000000000000000000000010011 G
b11100 L
b111 U
b111 P
b111 R
06
b0 E
19
#4280000
09
#4300000
00
05
0+
bx I
b1 E
b1000 R
b1000 P
b1000 U
b111 K
b10000000000000000000000011100 H
0J
b1000 M
b11100000000000000000000010011 G
b100000 L
19
#4320000
09
#4340000
1+
1J
b1001 M
b100000000000000000000000010011 G
b100100 L
b1001 U
b1001 P
b1001 R
b10 E
19
#4360000
09
#4380000
15
0+
bx I
b11 E
b1010 R
b1010 P
b1010 U
b1001 K
b10000000000000000000000100100 H
0J
b1010 M
b100100000000000000000000010011 G
b101000 L
19
#4400000
09
#4420000
1+
1J
b1011 M
b101000000000000000000000010011 G
b101100 L
b1011 U
b1011 P
b1011 R
16
b100 E
19
#4440000
09
#4460000
10
05
0+
bx I
06
b0 E
b1100 R
b1100 P
b1100 U
b1011 K
b10000000000000000000000101100 H
0J
b1100 M
b101100000000000000000000010011 G
b110000 L
19
#4480000
09
#4500000
1+
1J
b1101 M
b110000000000000000000000010011 G
b110100 L
b1101 U
b1101 P
b1101 R
b1 E
19
#4520000
09
#4540000
15
0+
bx I
b10 E
b1110 R
b1110 P
b1110 U
b1101 K
b10000000000000000000000110100 H
0J
b1110 M
b110100000000000000000000010011 G
b111000 L
19
#4560000
09
#4580000
1+
1J
b1111 M
b111000000000000000000000010011 G
b111100 L
b1111 U
b1111 P
b1111 R
b11 E
19
#4600000
09
#4620000
00
05
0+
b1 2
b1 B
bx I
16
b100 E
b10000 R
b1 O
b0 P
b10000 U
b1111 K
b10000000000000000000000111100 H
0J
b10000 M
b111100000000000000000000010011 G
b1000000 L
19
#4640000
09
#4660000
1+
1J
b10001 M
b1000000000000000000000000010011 G
b1000100 L
b10001 U
b1 P
b10001 R
06
b0 E
19
#4680000
09
#4700000
15
0+
bx I
b1 E
b10010 R
b10 P
b10010 U
b10001 K
b10000000000000000000001000100 H
0J
b10010 M
b1000100000000000000000000010011 G
b1001000 L
19
#4720000
09
#4740000
1+
1J
b10011 M
b1001000000000000000000000010011 G
b1001100 L
b10011 U
b11 P
b10011 R
b10 E
19
#4760000
09
#4780000
10
05
0+
bx I
b11 E
b10100 R
b100 P
b10100 U
b10011 K
b10000000000000000000001001100 H
0J
b10100 M
b1001100000000000000000000010011 G
b1010000 L
19
#4800000
09
#4820000
1+
1J
b10101 M
b1010000000000000000000000010011 G
b1010100 L
b10101 U
b101 P
b10101 R
16
b100 E
19
#4840000
09
#4860000
15
0+
bx I
06
b0 E
b10110 R
b110 P
b10110 U
b10101 K
b10000000000000000000001010100 H
0J
b10110 M
b1010100000000000000000000010011 G
b1011000 L
19
#4880000
09
#4900000
1+
1J
b10111 M
b1011000000000000000000000010011 G
b1011100 L
b10111 U
b111 P
b10111 R
b1 E
19
#4920000
09
#4940000
00
05
0+
bx I
b10 E
b11000 R
b1000 P
b11000 U
b10111 K
b10000000000000000000001011100 H
0J
b11000 M
b1011100000000000000000000010011 G
b1100000 L
19
#4960000
09
#4980000
1+
1J
b11001 M
b1100000000000000000000000010011 G
b1100100 L
b11001 U
b1001 P
b11001 R
b11 E
19
#5000000
09
#5020000
15
0+
bx I
16
b100 E
b11010 R
b1010 P
b11010 U
b11001 K
b10000000000000000000001100100 H
0J
b11010 M
b1100100000000000000000000010011 G
b1101000 L
19
#5040000
09
#5060000
1+
1J
b11011 M
b1101000000000000000000000010011 G
b1101100 L
b11011 U
b1011 P
b11011 R
06
b0 E
19
#5080000
09
#5100000
10
05
0+
bx I
b1 E
b11100 R
b1100 P
b11100 U
b11011 K
b10000000000000000000001101100 H
0J
b11100 M
b1101100000000000000000000010011 G
b1110000 L
19
#5120000
09
#5140000
1+
1J
b11101 M
b1110000000000000000000000010011 G
b1110100 L
b11101 U
b1101 P
b11101 R
b10 E
19
#5160000
09
#5180000
15
0+
bx I
b11 E
b11110 R
b1110 P
b11110 U
b11101 K
b10000000000000000000001110100 H
0J
b11110 M
b1110100000000000000000000010011 G
b1111000 L
19
#5200000
09
#5220000
1+
1J
b11111 M
b1111000000000000000000000010011 G
b1111100 L
b11111 U
b1111 P
b11111 R
16
b100 E
19
#5240000
09
#5260000
00
05
0+
b10 2
b10 B
bx I
06
b0 E
b100000 R
b10 O
b0 P
b100000 U
b11111 K
b10000000000000000000001111100 H
0J
b100000 M
b1111100000000000000000000010011 G
b10000000 L
19
#5280000
09
#5300000
1+
1J
b100001 M
b10000000000000000000000000010011 G
b10000100 L
b100001 U
b1 P
b100001 R
b1 E
19
#5320000
09
#5340000
15
0+
bx I
b10 E
b100010 R
b10 P
b100010 U
b100001 K
b10000000000000000000010000100 H
0J
b100010 M
b10000100000000000000000000010011 G
b10001000 L
19
#5360000
09
#5380000
1+
1J
b100011 M
b10001000000000000000000000010011 G
b10001100 L
b100011 U
b11 P
b100011 R
b11 E
19
#5400000
09
#5420000
10
05
0+
bx I
16
b100 E
b100100 R
b100 P
b100100 U
b100011 K
b10000000000000000000010001100 H
0J
b100100 M
b10001100000000000000000000010011 G
b10010000 L
19
#5440000
09
#5460000
1+
1J
b100101 M
b10010000000000000000000000010011 G
b10010100 L
b100101 U
b101 P
b100101 R
06
b0 E
19
#5480000
09
#5500000
15
0+
bx I
b1 E
b100110 R
b110 P
b100110 U
b100101 K
b10000000000000000000010010100 H
0J
b100110 M
b10010100000000000000000000010011 G
b10011000 L
19
#5520000
09
#5540000
1+
1J
b100111 M
b10011000000000000000000000010011 G
b10011100 L
b100111 U
b111 P
b100111 R
b10 E
19
#5560000
09
#5580000
00
05
0+
bx I
b11 E
b101000 R
b1000 P
b101000 U
b100111 K
b10000000000000000000010011100 H
0J
b101000 M
b10011100000000000000000000010011 G
b10100000 L
19
#5600000
09
#5620000
1+
1J
b101001 M
b10100000000000000000000000010011 G
b10100100 L
b101001 U
b1001 P
b101001 R
16
b100 E
19
#5640000
09
#5660000
15
0+
bx I
06
b0 E
b101010 R
b1010 P
b101010 U
b101001 K
b10000000000000000000010100100 H
0J
b101010 M
b10100100000000000000000000010011 G
b10101000 L
19
#5680000
09
#5700000
1+
1J
b101011 M
b10101000000000000000000000010011 G
b10101100 L
b101011 U
b1011 P
b101011 R
b1 E
19
#5720000
09
#5740000
10
05
0+
bx I
b10 E
b101100 R
b1100 P
b101100 U
b101011 K
b10000000000000000000010101100 H
0J
b101100 M
b10101100000000000000000000010011 G
b10110000 L
19
#5760000
09
#5780000
1+
1J
b101101 M
b10110000000000000000000000010011 G
b10110100 L
b101101 U
b1101 P
b101101 R
b11 E
19
#5800000
09
#5820000
15
0+
bx I
16
b100 E
b101110 R
b1110 P
b101110 U
b101101 K
b10000000000000000000010110100 H
0J
b101110 M
b10110100000000000000000000010011 G
b10111000 L
19
#5840000
09
#5860000
1+
1J
b101111 M
b10111000000000000000000000010011 G
b10111100 L
b101111 U
b1111 P
b101111 R
06
b0 E
19
#5880000
09
#5900000
00
05
0+
b11 2
b11 B
bx I
b1 E
b110000 R
b11 O
b0 P
b110000 U
b101111 K
b10000000000000000000010111100 H
0J
b110000 M
b10111100000000000000000000010011 G
b11000000 L
19
#5920000
09
#5940000
1+
1J
b110001 M
b11000000000000000000000000010011 G
b11000100 L
b110001 U
b1 P
b110001 R
b10 E
19
#5960000
09
#5980000
15
0+
bx I
b11 E
b110010 R
b10 P
b110010 U
b110001 K
b10000000000000000000011000100 H
0J
b110010 M
b11000100000000000000000000010011 G
b11001000 L
19
#6000000
09
#6020000
1+
1J
b110011 M
b11001000000000000000000000010011 G
b11001100 L
b110011 U
b11 P
b110011 R
16
b100 E
19
#6040000
09
